{
  "indexes": [
    {
      "collectionGroup": "incidents",
      "queryScope": "COLLECTION",
      "fields": [
        { "fieldPath": "status", "order": "ASCENDING" },
        { "fieldPath": "createdAt", "order": "DESCENDING" }
      ]
    },
    {
      "collectionGroup": "incidents",
      "queryScope": "COLLECTION",
      "fields": [
        { "fieldPath": "zoneId", "order": "ASCENDING" },
        { "fieldPath": "createdAt", "order": "DESCENDING" }
      ]
    },
    {
      "collectionGroup": "incidents",
      "queryScope": "COLLECTION",
      "fields": [
        { "fieldPath": "prioridad", "order": "ASCENDING" },
        { "fieldPath": "createdAt", "order": "DESCENDING" }
      ]
    },
    {
      "collectionGroup": "incidents",
      "queryScope": "COLLECTION",
      "fields": [
        { "fieldPath": "equipmentId", "order": "ASCENDING" },
        { "fieldPath": "createdAt", "order": "DESCENDING" }
      ]
    },
    {
      "collectionGroup": "incidents",
      "queryScope": "COLLECTION",
      "fields": [
        { "fieldPath": "reportadoPor", "order": "ASCENDING" },
        { "fieldPath": "createdAt", "order": "DESCENDING" }
      ]
    },
    {
      "collectionGroup": "equipment",
      "queryScope": "COLLECTION",
      "fields": [
        { "fieldPath": "zoneId", "order": "ASCENDING" },
        { "fieldPath": "nombre", "order": "ASCENDING" }
      ]
    },
    {
      "collectionGroup": "equipment",
      "queryScope": "COLLECTION",
      "fields": [
        { "fieldPath": "estado", "order": "ASCENDING" },
        { "fieldPath": "nombre", "order": "ASCENDING" }
      ]
    },
    {
      "collectionGroup": "preventiveTasks",
      "queryScope": "COLLECTION",
      "fields": [
        { "fieldPath": "equipmentId", "order": "ASCENDING" },
        { "fieldPath": "proximaEjecucion", "order": "ASCENDING" }
      ]
    },
    {
      "collectionGroup": "spareParts",
      "queryScope": "COLLECTION",
      "fields": [
        { "fieldPath": "categoria", "order": "ASCENDING" },
        { "fieldPath": "nombre", "order": "ASCENDING" }
      ]
    }
  ],
  "fieldOverrides": []
}
